llm_interpolate.py
llm_interpolate-0.1.dist-info/LICENSE
llm_interpolate-0.1.dist-info/METADATA
llm_interpolate-0.1.dist-info/WHEEL
llm_interpolate-0.1.dist-info/entry_points.txt
llm_interpolate-0.1.dist-info/top_level.txt
llm_interpolate-0.1.dist-info/RECORD
