Metadata-Version: 2.1
Name: llm-interpolate
Version: 0.1
Summary: LLM plugin for interpolating between embeddings
Author: Evangelos Lamprou
License: Apache-2.0
Project-URL: Homepage, https://github.com/vagos/llm-interpolate
Project-URL: Changelog, https://github.com/vagos/llm-interpolate/releases
Project-URL: Issues, https://github.com/vagos/llm-interpolate/issues
Project-URL: CI, https://github.com/vagos/llm-interpolate/actions
Classifier: License :: OSI Approved :: Apache Software License
License-File: LICENSE
Requires-Dist: llm >=0.9
Requires-Dist: numpy
Requires-Dist: scipy
Provides-Extra: test
Requires-Dist: pytest ; extra == 'test'
